euclid_msi/__init__.py
euclid_msi/backSPIN.py
euclid_msi/clustering.py
euclid_msi/data_management.py
euclid_msi/embedding.py
euclid_msi/euclid_casecontrol.py
euclid_msi/plotting.py
euclid_msi/postprocessing.py
euclid_msi/preprocessing.py
euclid_msi-0.0.6.dist-info/licenses/LICENSE
euclid_msi-0.0.6.dist-info/METADATA
euclid_msi-0.0.6.dist-info/WHEEL
euclid_msi-0.0.6.dist-info/top_level.txt
euclid_msi-0.0.6.dist-info/RECORD
