Metadata-Version: 2.4
Name: euclid_msi
Version: 0.0.6
Summary: A package for spatial lipidomics data analysis including preprocessing, embedding, clustering, postprocessing, case-control analysis, and plotting.
Author-email: Luca Fusar Bassini <luca.fusarbassini@epfl.ch>
License: BSD 3-Clause
Classifier: Programming Language :: Python :: 3
Classifier: Operating System :: OS Independent
Requires-Python: >=3.8
License-File: LICENSE
Requires-Dist: adjusttext==0.8
Requires-Dist: arviz==0.20.0
Requires-Dist: brotlipy==0.7.0
Requires-Dist: harmonypy==0.0.9
Requires-Dist: imblearn==0.0
Requires-Dist: rdkit==2023.9.5
Requires-Dist: reportlab==4.2.5
Requires-Dist: xgboost==1.7.6
Requires-Dist: pypdf2==3.0.1
Requires-Dist: anndata==0.10.9
Requires-Dist: igraph==0.10.5
Requires-Dist: jax==0.4.35
Requires-Dist: joblib==1.4.2
Requires-Dist: kneed==0.8.5
Requires-Dist: leidenalg==0.10.0
Requires-Dist: matplotlib==3.8.3
Requires-Dist: mofapy2==0.7.2
Requires-Dist: networkx==3.1
Requires-Dist: numba==0.60.0
Requires-Dist: numpy==1.26.4
Requires-Dist: numpyro==0.16.1
Requires-Dist: opentsne==1.0.1
Requires-Dist: optax==0.2.3
Requires-Dist: pandas==2.2.3
Requires-Dist: pathlib==1.0.1
Requires-Dist: plotly==5.14.1
Requires-Dist: scanpy==1.10.3
Requires-Dist: scipy==1.11.4
Requires-Dist: seaborn==0.13.2
Requires-Dist: squidpy==1.5.0
Requires-Dist: statsmodels==0.14.0
Requires-Dist: threadpoolctl==3.1.0
Requires-Dist: tqdm==4.67.1
Requires-Dist: zarr==2.14.2
Requires-Dist: opencv-python==4.11.0.86
Requires-Dist: dask<2025
Dynamic: license-file
